mptool.py
mptool-0.1.3.dist-info/LICENSE
mptool-0.1.3.dist-info/METADATA
mptool-0.1.3.dist-info/WHEEL
mptool-0.1.3.dist-info/top_level.txt
mptool-0.1.3.dist-info/zip-safe
mptool-0.1.3.dist-info/RECORD
