Metadata-Version: 2.1
Name: mptool
Version: 0.1.3
Summary: Enumeration and sampling of minimal pathways in metabolic (sub)networks.
Home-page: https://gitlab.com/csb.ethz/mptool
Author: Ove Øyås
Author-email: ove.oyas@nmbu.no
Project-URL: Source, https://gitlab.com/csb.ethz/mptool
Project-URL: Bug Tracker, https://gitlab.com/csb.ethz/mptool/-/issues
Keywords: metabolism,metabolic networks,metabolic pathways,minimal pathways,pathway analysis,pathway enumeration,pathway sampling,constraint-based modeling,metabolic modeling,systems biology
Classifier: Development Status :: 4 - Beta
Classifier: Intended Audience :: Science/Research
Classifier: Topic :: Scientific/Engineering :: Bio-Informatics
Classifier: Programming Language :: Python :: 3
Classifier: Natural Language :: English
Classifier: License :: OSI Approved :: MIT License
Classifier: Operating System :: OS Independent
Requires-Python: >=3
License-File: LICENSE
Requires-Dist: cobra >=0.17.1
Requires-Dist: gurobipy >=9.1.0
Requires-Dist: networkx >=2.4
Requires-Dist: numpy >=1.18.1
Requires-Dist: pytest >=4.6.9
